sqlite_utils_ask.py
sqlite_utils_ask-0.2.dist-info/LICENSE
sqlite_utils_ask-0.2.dist-info/METADATA
sqlite_utils_ask-0.2.dist-info/WHEEL
sqlite_utils_ask-0.2.dist-info/entry_points.txt
sqlite_utils_ask-0.2.dist-info/top_level.txt
sqlite_utils_ask-0.2.dist-info/RECORD
