Metadata-Version: 2.1
Name: sqlite-utils-ask
Version: 0.2
Summary: Ask questions of your data with LLM assistance
Author: Simon Willison
License: Apache-2.0
Project-URL: Homepage, https://github.com/simonw/sqlite-utils-ask
Project-URL: Changelog, https://github.com/simonw/sqlite-utils-ask/releases
Project-URL: Issues, https://github.com/simonw/sqlite-utils-ask/issues
Project-URL: CI, https://github.com/simonw/sqlite-utils-ask/actions
Classifier: License :: OSI Approved :: Apache Software License
License-File: LICENSE
Requires-Dist: sqlite-utils>=3.38
Requires-Dist: llm
Provides-Extra: test
Requires-Dist: pytest; extra == "test"
Requires-Dist: pytest-recording; extra == "test"
